README.md
setup.cfg
setup.py
snowflake/sqlalchemy/__init__.py
snowflake/sqlalchemy/base.py
snowflake/sqlalchemy/custom_commands.py
snowflake/sqlalchemy/custom_types.py
snowflake/sqlalchemy/snowdialect.py
snowflake/sqlalchemy/util.py
snowflake/sqlalchemy/version.py
snowflake_sqlalchemy_lite.egg-info/PKG-INFO
snowflake_sqlalchemy_lite.egg-info/SOURCES.txt
snowflake_sqlalchemy_lite.egg-info/dependency_links.txt
snowflake_sqlalchemy_lite.egg-info/entry_points.txt
snowflake_sqlalchemy_lite.egg-info/namespace_packages.txt
snowflake_sqlalchemy_lite.egg-info/requires.txt
snowflake_sqlalchemy_lite.egg-info/top_level.txt